[
    {
        "filled_ratio": 0.6,
        "trim_loss": 0.6213151927437641
    },
    {
        "filled_ratio": 0.3,
        "trim_loss": 0.41582676582676587
    },
    {
        "filled_ratio": 1.0,
        "trim_loss": 1.0
    },
    {
        "filled_ratio": 1.0,
        "trim_loss": 1.0
    },
    {
        "filled_ratio": 1.0,
        "trim_loss": 1.0
    },
    {
        "filled_ratio": 1.0,
        "trim_loss": 1.0
    },
    {
        "filled_ratio": 1.0,
        "trim_loss": 1.0
    },
    {
        "filled_ratio": 1.0,
        "trim_loss": 1.0
    },
    {
        "filled_ratio": 1.0,
        "trim_loss": 1.0
    },
    {
        "filled_ratio": 1.0,
        "trim_loss": 1.0
    }
]